asyncio_utils
