Metadata-Version: 1.1
Name: asyncio-utils
Version: 0.1.1
Summary: Asyncio utilities
Home-page: https://github.com/m-housh/asyncio_utils
Author: Michael Housh
Author-email: mhoush@houshhomeenergy.com
License: MIT license
Keywords: asyncio_utils
Platform: UNKNOWN
Classifier: Development Status :: 2 - Pre-Alpha
Classifier: Intended Audience :: Developers
Classifier: License :: OSI Approved :: MIT License
Classifier: Natural Language :: English
Classifier: Programming Language :: Python :: 3.6
